cm_feathers-1.0.2.dist-info/licenses/LICENSE.txt
feathers/__init__.py
feathers/feathers.py
cm_feathers-1.0.2.dist-info/METADATA
cm_feathers-1.0.2.dist-info/WHEEL
cm_feathers-1.0.2.dist-info/top_level.txt
cm_feathers-1.0.2.dist-info/RECORD
