Metadata-Version: 2.4
Name: cm_feathers
Version: 1.0.2
Summary: Matplotlib colormaps inspired by bird feathers
Author: Harrison Nicholls, email = harrison.nicholls@physics.ox.ac.uk
License-Expression: GPL-3.0-or-later
Project-URL: homepage, https://github.com/nichollsh/cm_feathers
Project-URL: issues, https://github.com/nichollsh/cm_feathers/issues
Keywords: Visualization,Color,Plotting
Requires-Python: >=3.9
License-File: LICENSE.txt
Requires-Dist: matplotlib
Requires-Dist: numpy
Provides-Extra: develop
Requires-Dist: coverage[toml]; extra == "develop"
Requires-Dist: pip-tools; extra == "develop"
Requires-Dist: pytest>=8.1; extra == "develop"
Requires-Dist: pre-commit; extra == "develop"
Requires-Dist: ruff; extra == "develop"
Dynamic: license-file
